TCLIService/TCLIService.py
TCLIService/__init__.py
TCLIService/constants.py
TCLIService/ttypes.py
pycquery/__init__.py
pycquery/common.py
pycquery/exc.py
pycquery/hive.py
pycquery/sqlalchemy_hive.py
pycquery_krb/__init__.py
pycquery_krb/aioclient.py
pycquery_krb/client.py
pycquery_krb/security.py
pycquery_krb/common/__init__.py
pycquery_krb/common/ccache.py
pycquery_krb/common/conf.py
pycquery_krb/common/constants.py
pycquery_krb/common/creds.py
pycquery_krb/common/keytab.py
pycquery_krb/common/proxy.py
pycquery_krb/common/spn.py
pycquery_krb/common/target.py
pycquery_krb/common/url.py
pycquery_krb/common/utils.py
pycquery_krb/crypto/BASE.py
pycquery_krb/crypto/RC4.py
pycquery_krb/crypto/__init__.py
pycquery_krb/crypto/hashing.py
pycquery_krb/crypto/AES/AES.py
pycquery_krb/crypto/AES/__init__.py
pycquery_krb/crypto/AES/blockfeeder.py
pycquery_krb/crypto/AES/util.py
pycquery_krb/crypto/DES/DES.py
pycquery_krb/crypto/DES/__init__.py
pycquery_krb/crypto/PBKDF2/__init__.py
pycquery_krb/crypto/PBKDF2/pbkdf2.py
pycquery_krb/crypto/RC4/RC4.py
pycquery_krb/crypto/RC4/__init__.py
pycquery_krb/gssapi/__init__.py
pycquery_krb/gssapi/channelbindings.py
pycquery_krb/gssapi/gssapi.py
pycquery_krb/network/__init__.py
pycquery_krb/network/aioclientsocket.py
pycquery_krb/network/aioclientsockssocket.py
pycquery_krb/network/clientsocket.py
pycquery_krb/network/selector.py
pycquery_krb/protocol/__init__.py
pycquery_krb/protocol/asn1_structs.py
pycquery_krb/protocol/constants.py
pycquery_krb/protocol/encryption.py
pycquery_krb/protocol/errors.py
pycquery_krb/protocol/structures.py
PyCQuery-1.0.7.dist-info/LICENSE
PyCQuery-1.0.7.dist-info/METADATA
PyCQuery-1.0.7.dist-info/NOTICE
PyCQuery-1.0.7.dist-info/WHEEL
PyCQuery-1.0.7.dist-info/top_level.txt
PyCQuery-1.0.7.dist-info/RECORD
