Metadata-Version: 2.1
Name: PyCQuery
Version: 1.0.7
Summary: Python interface to Hive with pure-python Kerberos support
Home-page: https://github.com/naver/PyCQuery
Author: NAVER Corp.
License: Apache License, Version 2.0
Platform: UNKNOWN
Classifier: Programming Language :: Python :: 3
Classifier: Programming Language :: Python :: 3.6
Classifier: Programming Language :: Python :: 3.7
Classifier: Programming Language :: Python :: 3.8
Classifier: Programming Language :: Python :: 3.9
Requires-Python: >=3.6
License-File: LICENSE
License-File: NOTICE
Requires-Dist: future (>=0.18.2)
Requires-Dist: python-dateutil (>=2.8.1)
Requires-Dist: kazoo (>=2.8.0)
Requires-Dist: requests (>=2.25.1)
Requires-Dist: thrift (>=0.13.0)
Requires-Dist: asn1crypto (>=1.4.0)
Requires-Dist: asysocks (>=0.1.0)
Requires-Dist: pyasn1 (>=0.4.8)
Requires-Dist: pytimeparse (>=1.1.8)
